beque/__init__.py
beque/beque.py
beque-0.1.0.dist-info/METADATA
beque-0.1.0.dist-info/WHEEL
beque-0.1.0.dist-info/licenses/LICENSE
beque-0.1.0.dist-info/RECORD
