Metadata-Version: 2.4
Name: beque
Version: 0.1.0
Summary: Asynchronous In-Memory Batch Queue Processor
Author-email: Punit Arani <punitsai36@gmail.com>
License-Expression: MIT
License-File: LICENSE
Keywords: async,batch,processing,queue
Classifier: Development Status :: 4 - Beta
Classifier: Intended Audience :: Developers
Classifier: Programming Language :: Python :: 3
Classifier: Programming Language :: Python :: 3.8
Classifier: Programming Language :: Python :: 3.9
Classifier: Programming Language :: Python :: 3.10
Classifier: Programming Language :: Python :: 3.11
Classifier: Programming Language :: Python :: 3.12
Classifier: Programming Language :: Python :: 3.13
Requires-Python: >=3.8
